{
  "id": "2013020164",
  "sid": "2013",
  "t": "02",
  "gn": "0164",
  "utcStart": "2013-10-26 19:00:00+0000",
  "easternStart": "2013-10-26 15:00:00",
  "summary": "",
  "h": {
    "ab": "PHX",
    "record": "5-2-2",
    "live": "",
    "replayShort": "",
    "replayShortNumber": 0,
    "replayFull": "",
    "replayFullNumber": 0
  },
  "a": {
    "ab": "EDM",
    "record": "2-6-1",
    "live": "",
    "replayShort": "",
    "replayShortNumber": 0,
    "replayFull": "",
    "replayFullNumber": 0
  },
  "pbp": []
}