{
  "id": "2013020145",
  "sid": "2013",
  "t": "02",
  "gn": "0145",
  "utcStart": "2013-10-25 00:00:00+0000",
  "easternStart": "2013-10-24 20:00:00",
  "summary": "",
  "h": {
    "ab": "MIN",
    "record": "3-3-3",
    "live": "",
    "replayShort": "",
    "replayShortNumber": 0,
    "replayFull": "",
    "replayFullNumber": 0
  },
  "a": {
    "ab": "CAR",
    "record": "4-2-3",
    "live": "",
    "replayShort": "",
    "replayShortNumber": 0,
    "replayFull": "",
    "replayFullNumber": 0
  },
  "pbp": []
}